vocably/__init__.py
vocably/constants.py
vocably/Preprocessing/__init__.py
vocably/Preprocessing/summarizer.py
vocably/Preprocessing/text.py
vocably/cli/__init__.py
vocably/cli/main.py
vocably/featurizer/__init__.py
vocably/featurizer/text.py
vocably/grammercheck/Grammer_checker.py
vocably/grammercheck/__init__.py
vocably/grammercheck/grammerchecker.py
vocably/paraphraser/__init__.py
vocably/paraphraser/paraphrase.py
vocably/spellcheck/__init__.py
vocably/spellcheck/checker.py
vocably/summarizer/__init__.py
vocably-0.0.9.dist-info/LICENSE
vocably-0.0.9.dist-info/METADATA
vocably-0.0.9.dist-info/WHEEL
vocably-0.0.9.dist-info/entry_points.txt
vocably-0.0.9.dist-info/top_level.txt
vocably-0.0.9.dist-info/RECORD
