Metadata-Version: 2.1
Name: vocably
Version: 0.0.9
Summary: Vocably is a Natural Language Framework written in Python for Language based Tasks.
Home-page: https://github.com/Nandhini25S/Vocably
Author: Nandhini, Sarika
Author-email: nandhinisiva2561@gmail.com
License: MIT
Classifier: Programming Language :: Python :: 3
Classifier: License :: OSI Approved :: MIT License
Classifier: Operating System :: OS Independent
Requires-Python: >=3.7,<4
License-File: LICENSE
Requires-Dist: click (~=8.0.1)
Requires-Dist: jsonpickle (~=2.1.0)
Requires-Dist: pyyaml (~=6.0)
Requires-Dist: torch (~=2.0.0)
Requires-Dist: regex
Requires-Dist: scikit-learn (~=1.1.2)
Requires-Dist: rich (~=12.6.0)
Requires-Dist: transformers (~=4.22.0)
Requires-Dist: gensim (~=4.3.1)
Requires-Dist: nltk (~=3.7)
Requires-Dist: spacy (~=3.4.1)
Requires-Dist: smart-open (~=5.2.1)
Requires-Dist: sentencepiece (~=0.1.98)
Requires-Dist: protobuf (~=3.20.0)
Requires-Dist: happytransformer (~=2.4.1)
Requires-Dist: aiohttp (~=3.7.4)
